{
  "content": [
    {
      "content": null,
      "created": "2024-08-27T17:22:49.685764Z",
      "format": null,
      "hash": null,
      "hash_algorithm": null,
      "last_modified": "2024-08-27T17:22:49.685764Z",
      "mimetype": null,
      "name": "4.3",
      "path": "packages_wasmbuilt/bin/emscripten/contrib/4.3",
      "size": null,
      "type": "directory",
      "writable": true
    }
  ],
  "created": "2024-08-27T17:22:49.649764Z",
  "format": "json",
  "hash": null,
  "hash_algorithm": null,
  "last_modified": "2024-08-27T17:22:49.649764Z",
  "mimetype": null,
  "name": "contrib",
  "path": "packages_wasmbuilt/bin/emscripten/contrib",
  "size": null,
  "type": "directory",
  "writable": true
}